LICENSE
MANIFEST.in
README.rst
setup.py
buildout_platform_versions/__init__.py
buildout_platform_versions.egg-info/PKG-INFO
buildout_platform_versions.egg-info/SOURCES.txt
buildout_platform_versions.egg-info/dependency_links.txt
buildout_platform_versions.egg-info/entry_points.txt
buildout_platform_versions.egg-info/requires.txt
buildout_platform_versions.egg-info/top_level.txt
buildout_platform_versions.egg-info/zip-safe