Metadata-Version: 1.1
Name: buildout-platform-versions
Version: 1.2.1
Summary: Dependency version management forklift for buildout.
Home-page: http://github.com/zillow/buildout-platform-versions
Author: Jonathan Ultis
Author-email: jonathanu@zillow.com
License: The MIT License (MIT)
